{
    "unac-1.8.0": {
        "unac.h": [
            {
                "name": "unac_string_utf16",
                "start": 78,
                "end": 79
            },
            {
                "name": "unac_string",
                "start": 94,
                "end": 96
            }
        ],
        "unactest.c": [
            {
                "name": "main",
                "start": 32,
                "end": 53
            }
        ],
        "unac.c": [
            {
                "name": "debug_print",
                "start": 13634,
                "end": 13636
            },
            {
                "name": "utf16be",
                "start": 13646,
                "end": 13662
            },
            {
                "name": "unac_string_utf16",
                "start": 13664,
                "end": 13748
            },
            {
                "name": "convert",
                "start": 13752,
                "end": 13754
            },
            {
                "name": "convert",
                "start": 13763,
                "end": 13859
            },
            {
                "name": "unac_string",
                "start": 13861,
                "end": 13894
            },
            {
                "name": "unac_version",
                "start": 13897,
                "end": 13900
            }
        ],
        "unactest1.c": [
            {
                "name": "main",
                "start": 439,
                "end": 497
            }
        ],
        "unaccent.c": [
            {
                "name": "usage",
                "start": 31,
                "end": 47
            },
            {
                "name": "main",
                "start": 49,
                "end": 137
            }
        ]
    }
}