{
    "binclock-1.5": {
        "src/binclock.c": [
            {
                "name": "bclock_usage",
                "start": 43,
                "end": 56
            },
            {
                "name": "bclock_version",
                "start": 59,
                "end": 62
            },
            {
                "name": "printbin",
                "start": 83,
                "end": 86
            },
            {
                "name": "traditional_outpt",
                "start": 88,
                "end": 101
            },
            {
                "name": "mkcolorint_check",
                "start": 103,
                "end": 116
            },
            {
                "name": "parse_config",
                "start": 118,
                "end": 169
            },
            {
                "name": "bin_time",
                "start": 173,
                "end": 270
            },
            {
                "name": "main",
                "start": 273,
                "end": 338
            }
        ]
    }
}