{
    "rotter-0.9": {
        "src/jack.c": [
            {
                "name": "callback_jack",
                "start": 52,
                "end": 80
            },
            {
                "name": "shutdown_callback_jack",
                "start": 84,
                "end": 91
            },
            {
                "name": "connect_jack_port",
                "start": 95,
                "end": 105
            },
            {
                "name": "autoconnect_jack_ports",
                "start": 109,
                "end": 132
            },
            {
                "name": "init_jack",
                "start": 136,
                "end": 179
            },
            {
                "name": "deinit_jack",
                "start": 183,
                "end": 203
            }
        ],
        "src/mpegaudiofile.c": [
            {
                "name": "gethostname_fqdn",
                "start": 75,
                "end": 109
            },
            {
                "name": "write_id3v1",
                "start": 114,
                "end": 164
            },
            {
                "name": "close_mpegaudio_file",
                "start": 169,
                "end": 189
            },
            {
                "name": "open_mpegaudio_file",
                "start": 192,
                "end": 209
            }
        ],
        "src/rotter.c": [
            {
                "name": "termination_handler",
                "start": 96,
                "end": 109
            },
            {
                "name": "rotter_log",
                "start": 113,
                "end": 156
            },
            {
                "name": "start_of_hour",
                "start": 162,
                "end": 175
            },
            {
                "name": "directory_exists",
                "start": 178,
                "end": 195
            },
            {
                "name": "mkdir_p",
                "start": 198,
                "end": 234
            },
            {
                "name": "time_to_filepath_flat",
                "start": 237,
                "end": 255
            },
            {
                "name": "time_to_filepath_hierarchy",
                "start": 258,
                "end": 285
            },
            {
                "name": "time_to_filepath_combo",
                "start": 288,
                "end": 314
            },
            {
                "name": "time_to_filepath_dailydir",
                "start": 316,
                "end": 342
            },
            {
                "name": "main_loop",
                "start": 345,
                "end": 422
            },
            {
                "name": "str_tolower",
                "start": 425,
                "end": 434
            },
            {
                "name": "usage",
                "start": 438,
                "end": 474
            },
            {
                "name": "main",
                "start": 477,
                "end": 608
            }
        ],
        "src/deletefiles.c": [
            {
                "name": "delete_file",
                "start": 39,
                "end": 62
            },
            {
                "name": "get_file_device",
                "start": 65,
                "end": 75
            },
            {
                "name": "delete_files_in_dir",
                "start": 78,
                "end": 126
            },
            {
                "name": "delete_files",
                "start": 131,
                "end": 164
            }
        ]
    }
}